zope/mimetype/README.rst
zope/mimetype/TODO.rst
zope/mimetype/__init__.py
zope/mimetype/character-sets.txt
zope/mimetype/codec.py
zope/mimetype/codec.rst
zope/mimetype/configure.rst
zope/mimetype/configure.zcml
zope/mimetype/constraints.rst
zope/mimetype/contentinfo.py
zope/mimetype/contentinfo.rst
zope/mimetype/event.py
zope/mimetype/event.rst
zope/mimetype/i18n.py
zope/mimetype/interfaces.py
zope/mimetype/meta.zcml
zope/mimetype/mtypes.py
zope/mimetype/retrieving_mime_types.rst
zope/mimetype/source.py
zope/mimetype/source.rst
zope/mimetype/typegetter.py
zope/mimetype/typegetter.rst
zope/mimetype/types.csv
zope/mimetype/utils.py
zope/mimetype/utils.rst
zope/mimetype/widget.py
zope/mimetype/widget.rst
zope/mimetype/zcml.py
zope/mimetype/icons/archive.png
zope/mimetype/icons/audio.gif
zope/mimetype/icons/binary.gif
zope/mimetype/icons/css.gif
zope/mimetype/icons/document.gif
zope/mimetype/icons/html.gif
zope/mimetype/icons/image.gif
zope/mimetype/icons/javascript.gif
zope/mimetype/icons/ms-excel.gif
zope/mimetype/icons/ms-powerpoint.gif
zope/mimetype/icons/ms-project.gif
zope/mimetype/icons/ms-word.gif
zope/mimetype/icons/octet-stream.gif
zope/mimetype/icons/oo-calc.png
zope/mimetype/icons/oo-impress.png
zope/mimetype/icons/oo-writer.png
zope/mimetype/icons/pdf.gif
zope/mimetype/icons/python.gif
zope/mimetype/icons/video.png
zope/mimetype/icons/wordperfect.gif
zope/mimetype/icons/xml.gif
zope/mimetype/icons/xsl.gif
zope/mimetype/tests/__init__.py
zope/mimetype/tests/test_codec.py
zope/mimetype/tests/test_contentinfo.py
zope/mimetype/tests/test_doctests.py
zope/mimetype/tests/test_source.py
zope/mimetype/tests/test_typegetter.py
zope/mimetype/tests/test_zcml.py
zope_mimetype-4.0.dist-info/licenses/LICENSE.txt
zope_mimetype-4.0.dist-info/METADATA
zope_mimetype-4.0.dist-info/WHEEL
zope_mimetype-4.0.dist-info/top_level.txt
zope_mimetype-4.0.dist-info/RECORD
