Metadata-Version: 2.4
Name: zope.mimetype
Version: 4.0
Summary: A simple package for working with MIME content types
Home-page: https://github.com/zopefoundation/zope.mimetype
Author: Zope Foundation and Contributors
Author-email: zope-dev@zope.dev
License: ZPL-2.1
Keywords: file content mimetype
Classifier: Development Status :: 5 - Production/Stable
Classifier: Environment :: Web Environment
Classifier: Intended Audience :: Developers
Classifier: License :: OSI Approved :: Zope Public License
Classifier: Programming Language :: Python
Classifier: Programming Language :: Python :: 3
Classifier: Programming Language :: Python :: 3.9
Classifier: Programming Language :: Python :: 3.10
Classifier: Programming Language :: Python :: 3.11
Classifier: Programming Language :: Python :: 3.12
Classifier: Programming Language :: Python :: 3.13
Classifier: Programming Language :: Python :: Implementation :: CPython
Classifier: Programming Language :: Python :: Implementation :: PyPy
Classifier: Natural Language :: English
Classifier: Operating System :: OS Independent
Classifier: Topic :: Internet :: WWW/HTTP
Classifier: Framework :: Zope :: 3
Requires-Python: >=3.9
License-File: LICENSE.txt
Requires-Dist: setuptools
Requires-Dist: zope.component
Requires-Dist: zope.configuration
Requires-Dist: zope.contenttype>=3.5
Requires-Dist: zope.event
Requires-Dist: zope.i18n
Requires-Dist: zope.i18nmessageid
Requires-Dist: zope.interface
Requires-Dist: zope.schema
Requires-Dist: zope.security
Provides-Extra: test
Requires-Dist: zope.browser; extra == "test"
Requires-Dist: zope.browserresource; extra == "test"
Requires-Dist: zope.formlib>=4.0; extra == "test"
Requires-Dist: zope.publisher; extra == "test"
Requires-Dist: zope.testing; extra == "test"
Requires-Dist: zope.testrunner>=6.4; extra == "test"
Provides-Extra: browser
Requires-Dist: zope.browser; extra == "browser"
Requires-Dist: zope.browserresource; extra == "browser"
Requires-Dist: zope.formlib>=4.0; extra == "browser"
Requires-Dist: zope.publisher; extra == "browser"
Provides-Extra: docs
Requires-Dist: Sphinx; extra == "docs"
Requires-Dist: sphinx_rtd_theme; extra == "docs"
Requires-Dist: repoze.sphinx.autointerface; extra == "docs"
Requires-Dist: zope.browser; extra == "docs"
Requires-Dist: zope.browserresource; extra == "docs"
Requires-Dist: zope.formlib>=4.0; extra == "docs"
Requires-Dist: zope.publisher; extra == "docs"
Dynamic: author
Dynamic: author-email
Dynamic: classifier
Dynamic: description
Dynamic: home-page
Dynamic: keywords
Dynamic: license
Dynamic: license-file
Dynamic: provides-extra
Dynamic: requires-dist
Dynamic: requires-python
Dynamic: summary
